{"assets/images/weather/100.png":["assets/images/weather/100.png","assets/images/weather/2.0x/100.png","assets/images/weather/3.0x/100.png"],"assets/images/weather/101.png":["assets/images/weather/101.png","assets/images/weather/2.0x/101.png","assets/images/weather/3.0x/101.png"],"assets/images/weather/102.png":["assets/images/weather/102.png","assets/images/weather/2.0x/102.png","assets/images/weather/3.0x/102.png"],"assets/images/weather/103.png":["assets/images/weather/103.png","assets/images/weather/2.0x/103.png","assets/images/weather/3.0x/103.png"],"assets/images/weather/104.png":["assets/images/weather/104.png","assets/images/weather/2.0x/104.png","assets/images/weather/3.0x/104.png"],"assets/images/weather/200.png":["assets/images/weather/200.png","assets/images/weather/2.0x/200.png","assets/images/weather/3.0x/200.png"],"assets/images/weather/201.png":["assets/images/weather/201.png","assets/images/weather/2.0x/201.png","assets/images/weather/3.0x/201.png"],"assets/images/weather/202.png":["assets/images/weather/202.png","assets/images/weather/2.0x/202.png","assets/images/weather/3.0x/202.png"],"assets/images/weather/203.png":["assets/images/weather/203.png","assets/images/weather/2.0x/203.png","assets/images/weather/3.0x/203.png"],"assets/images/weather/204.png":["assets/images/weather/204.png","assets/images/weather/2.0x/204.png","assets/images/weather/3.0x/204.png"],"assets/images/weather/205.png":["assets/images/weather/205.png","assets/images/weather/2.0x/205.png","assets/images/weather/3.0x/205.png"],"assets/images/weather/206.png":["assets/images/weather/206.png","assets/images/weather/2.0x/206.png","assets/images/weather/3.0x/206.png"],"assets/images/weather/207.png":["assets/images/weather/207.png","assets/images/weather/2.0x/207.png","assets/images/weather/3.0x/207.png"],"assets/images/weather/208.png":["assets/images/weather/208.png","assets/images/weather/2.0x/208.png","assets/images/weather/3.0x/208.png"],"assets/images/weather/209.png":["assets/images/weather/209.png","assets/images/weather/2.0x/209.png","assets/images/weather/3.0x/209.png"],"assets/images/weather/210.png":["assets/images/weather/210.png","assets/images/weather/2.0x/210.png","assets/images/weather/3.0x/210.png"],"assets/images/weather/211.png":["assets/images/weather/211.png","assets/images/weather/2.0x/211.png","assets/images/weather/3.0x/211.png"],"assets/images/weather/212.png":["assets/images/weather/212.png","assets/images/weather/2.0x/212.png","assets/images/weather/3.0x/212.png"],"assets/images/weather/213.png":["assets/images/weather/213.png","assets/images/weather/2.0x/213.png","assets/images/weather/3.0x/213.png"],"assets/images/weather/300.png":["assets/images/weather/300.png","assets/images/weather/2.0x/300.png","assets/images/weather/3.0x/300.png"],"assets/images/weather/301.png":["assets/images/weather/301.png","assets/images/weather/2.0x/301.png","assets/images/weather/3.0x/301.png"],"assets/images/weather/302.png":["assets/images/weather/302.png","assets/images/weather/2.0x/302.png","assets/images/weather/3.0x/302.png"],"assets/images/weather/303.png":["assets/images/weather/303.png","assets/images/weather/2.0x/303.png","assets/images/weather/3.0x/303.png"],"assets/images/weather/304.png":["assets/images/weather/304.png","assets/images/weather/2.0x/304.png","assets/images/weather/3.0x/304.png"],"assets/images/weather/305.png":["assets/images/weather/305.png","assets/images/weather/2.0x/305.png","assets/images/weather/3.0x/305.png"],"assets/images/weather/306.png":["assets/images/weather/306.png","assets/images/weather/2.0x/306.png","assets/images/weather/3.0x/306.png"],"assets/images/weather/307.png":["assets/images/weather/307.png","assets/images/weather/2.0x/307.png","assets/images/weather/3.0x/307.png"],"assets/images/weather/308.png":["assets/images/weather/308.png","assets/images/weather/2.0x/308.png","assets/images/weather/3.0x/308.png"],"assets/images/weather/309.png":["assets/images/weather/309.png","assets/images/weather/2.0x/309.png","assets/images/weather/3.0x/309.png"],"assets/images/weather/310.png":["assets/images/weather/310.png","assets/images/weather/2.0x/310.png","assets/images/weather/3.0x/310.png"],"assets/images/weather/311.png":["assets/images/weather/311.png","assets/images/weather/2.0x/311.png","assets/images/weather/3.0x/311.png"],"assets/images/weather/312.png":["assets/images/weather/312.png","assets/images/weather/2.0x/312.png","assets/images/weather/3.0x/312.png"],"assets/images/weather/313.png":["assets/images/weather/313.png","assets/images/weather/2.0x/313.png","assets/images/weather/3.0x/313.png"],"assets/images/weather/314.png":["assets/images/weather/314.png","assets/images/weather/2.0x/314.png","assets/images/weather/3.0x/314.png"],"assets/images/weather/315.png":["assets/images/weather/315.png","assets/images/weather/2.0x/315.png","assets/images/weather/3.0x/315.png"],"assets/images/weather/316.png":["assets/images/weather/316.png","assets/images/weather/2.0x/316.png","assets/images/weather/3.0x/316.png"],"assets/images/weather/317.png":["assets/images/weather/317.png","assets/images/weather/2.0x/317.png","assets/images/weather/3.0x/317.png"],"assets/images/weather/318.png":["assets/images/weather/318.png","assets/images/weather/2.0x/318.png","assets/images/weather/3.0x/318.png"],"assets/images/weather/399.png":["assets/images/weather/399.png","assets/images/weather/2.0x/399.png","assets/images/weather/3.0x/399.png"],"assets/images/weather/400.png":["assets/images/weather/400.png","assets/images/weather/2.0x/400.png","assets/images/weather/3.0x/400.png"],"assets/images/weather/401.png":["assets/images/weather/401.png","assets/images/weather/2.0x/401.png","assets/images/weather/3.0x/401.png"],"assets/images/weather/402.png":["assets/images/weather/402.png","assets/images/weather/2.0x/402.png","assets/images/weather/3.0x/402.png"],"assets/images/weather/403.png":["assets/images/weather/403.png","assets/images/weather/2.0x/403.png","assets/images/weather/3.0x/403.png"],"assets/images/weather/404.png":["assets/images/weather/404.png","assets/images/weather/2.0x/404.png","assets/images/weather/3.0x/404.png"],"assets/images/weather/405.png":["assets/images/weather/405.png","assets/images/weather/2.0x/405.png","assets/images/weather/3.0x/405.png"],"assets/images/weather/406.png":["assets/images/weather/406.png","assets/images/weather/2.0x/406.png","assets/images/weather/3.0x/406.png"],"assets/images/weather/407.png":["assets/images/weather/407.png","assets/images/weather/2.0x/407.png","assets/images/weather/3.0x/407.png"],"assets/images/weather/408.png":["assets/images/weather/408.png","assets/images/weather/2.0x/408.png","assets/images/weather/3.0x/408.png"],"assets/images/weather/409.png":["assets/images/weather/409.png","assets/images/weather/2.0x/409.png","assets/images/weather/3.0x/409.png"],"assets/images/weather/410.png":["assets/images/weather/410.png","assets/images/weather/2.0x/410.png","assets/images/weather/3.0x/410.png"],"assets/images/weather/499.png":["assets/images/weather/499.png","assets/images/weather/2.0x/499.png","assets/images/weather/3.0x/499.png"],"assets/images/weather/500.png":["assets/images/weather/500.png","assets/images/weather/2.0x/500.png","assets/images/weather/3.0x/500.png"],"assets/images/weather/501.png":["assets/images/weather/501.png","assets/images/weather/2.0x/501.png","assets/images/weather/3.0x/501.png"],"assets/images/weather/502.png":["assets/images/weather/502.png","assets/images/weather/2.0x/502.png","assets/images/weather/3.0x/502.png"],"assets/images/weather/503.png":["assets/images/weather/503.png","assets/images/weather/2.0x/503.png","assets/images/weather/3.0x/503.png"],"assets/images/weather/504.png":["assets/images/weather/504.png","assets/images/weather/2.0x/504.png","assets/images/weather/3.0x/504.png"],"assets/images/weather/507.png":["assets/images/weather/507.png","assets/images/weather/2.0x/507.png","assets/images/weather/3.0x/507.png"],"assets/images/weather/508.png":["assets/images/weather/508.png","assets/images/weather/2.0x/508.png","assets/images/weather/3.0x/508.png"],"assets/images/weather/509.png":["assets/images/weather/509.png","assets/images/weather/2.0x/509.png","assets/images/weather/3.0x/509.png"],"assets/images/weather/510.png":["assets/images/weather/510.png","assets/images/weather/2.0x/510.png","assets/images/weather/3.0x/510.png"],"assets/images/weather/511.png":["assets/images/weather/511.png","assets/images/weather/2.0x/511.png","assets/images/weather/3.0x/511.png"],"assets/images/weather/512.png":["assets/images/weather/512.png","assets/images/weather/2.0x/512.png","assets/images/weather/3.0x/512.png"],"assets/images/weather/513.png":["assets/images/weather/513.png","assets/images/weather/2.0x/513.png","assets/images/weather/3.0x/513.png"],"assets/images/weather/514.png":["assets/images/weather/514.png","assets/images/weather/2.0x/514.png","assets/images/weather/3.0x/514.png"],"assets/images/weather/515.png":["assets/images/weather/515.png","assets/images/weather/2.0x/515.png","assets/images/weather/3.0x/515.png"],"assets/images/weather/900.png":["assets/images/weather/900.png","assets/images/weather/2.0x/900.png","assets/images/weather/3.0x/900.png"],"assets/images/weather/901.png":["assets/images/weather/901.png","assets/images/weather/2.0x/901.png","assets/images/weather/3.0x/901.png"],"assets/images/weather/999.png":["assets/images/weather/999.png","assets/images/weather/2.0x/999.png","assets/images/weather/3.0x/999.png"],"packages/cupertino_icons/assets/CupertinoIcons.ttf":["packages/cupertino_icons/assets/CupertinoIcons.ttf"],"fonts/VarelaRound-Regular.ttf":["fonts/VarelaRound-Regular.ttf"],"assets/images/air_pressure.png":["assets/images/air_pressure.png","assets/images/2.0x/air_pressure.png","assets/images/3.0x/air_pressure.png"],"assets/langs/en-US.json":["assets/langs/en-US.json"],"assets/images/humidity.png":["assets/images/humidity.png","assets/images/2.0x/humidity.png","assets/images/3.0x/humidity.png"],"packages/material_design_icons_flutter/lib/fonts/materialdesignicons-webfont.ttf":["packages/material_design_icons_flutter/lib/fonts/materialdesignicons-webfont.ttf"],"assets/images/search.png":["assets/images/search.png","assets/images/2.0x/search.png","assets/images/3.0x/search.png"],"assets/images/setting.png":["assets/images/setting.png","assets/images/2.0x/setting.png","assets/images/3.0x/setting.png"],"assets/images/somatosensory.png":["assets/images/somatosensory.png","assets/images/2.0x/somatosensory.png","assets/images/3.0x/somatosensory.png"],"assets/images/wind_direction.png":["assets/images/wind_direction.png","assets/images/2.0x/wind_direction.png","assets/images/3.0x/wind_direction.png"],"assets/langs/zh-CN.json":["assets/langs/zh-CN.json"]}